make87_messages_ros2
