Metadata-Version: 2.4
Name: make87_messages_ros2_pb4
Version: 0.2.0
Author-email: Nisse Knudsen <nisse@make87.com>
Requires-Python: <3.13,>=3.9
Requires-Dist: make87_messages_pb4
Requires-Dist: protobuf<5.0,>=4.22
Provides-Extra: dev
Requires-Dist: pre-commit; extra == "dev"
